MANIFEST.in
setup.py
girlfriend/__init__.py
girlfriend/exception.py
girlfriend.egg-info/PKG-INFO
girlfriend.egg-info/SOURCES.txt
girlfriend.egg-info/dependency_links.txt
girlfriend.egg-info/entry_points.txt
girlfriend.egg-info/pbr.json
girlfriend.egg-info/requires.txt
girlfriend.egg-info/top_level.txt
girlfriend/data/__init__.py
girlfriend/data/exception.py
girlfriend/data/table.py
girlfriend/plugin/__init__.py
girlfriend/plugin/crawl.py
girlfriend/plugin/csv.py
girlfriend/plugin/data.py
girlfriend/plugin/excel.py
girlfriend/plugin/hadoop_streaming.py
girlfriend/plugin/json.py
girlfriend/plugin/mail.py
girlfriend/plugin/orm.py
girlfriend/plugin/table.py
girlfriend/plugin/text.py
girlfriend/testing/__init__.py
girlfriend/testing/runalltests.py
girlfriend/testing/data/__init__.py
girlfriend/testing/data/table.py
girlfriend/testing/plugin/__init__.py
girlfriend/testing/plugin/crawl.py
girlfriend/testing/plugin/csv.py
girlfriend/testing/plugin/excel.py
girlfriend/testing/plugin/json.py
girlfriend/testing/plugin/mail.py
girlfriend/testing/plugin/orm.py
girlfriend/testing/plugin/plugin.py
girlfriend/testing/plugin/table.py
girlfriend/testing/plugin/text.py
girlfriend/testing/tools/__init__.py
girlfriend/testing/tools/test_workflow.py
girlfriend/testing/util/__init__.py
girlfriend/testing/util/concurrent.py
girlfriend/testing/util/config.py
girlfriend/testing/util/file_template.py
girlfriend/testing/util/lang.py
girlfriend/testing/util/time.py
girlfriend/testing/util/validating.py
girlfriend/testing/workflow/__init__.py
girlfriend/testing/workflow/concurrent.py
girlfriend/testing/workflow/gfworkflow.py
girlfriend/testing/workflow/protocol.py
girlfriend/tools/__init__.py
girlfriend/tools/gf_config.py
girlfriend/tools/gf_gen.py
girlfriend/tools/gf_test_data.py
girlfriend/tools/gf_workflow.py
girlfriend/tools/code_template/__init__.py
girlfriend/tools/code_template/plugin_code_meta.py
girlfriend/tools/code_template/workflow_template.py
girlfriend/util/__init__.py
girlfriend/util/cmdargs.py
girlfriend/util/concurrent.py
girlfriend/util/config.py
girlfriend/util/file_template.py
girlfriend/util/lang.py
girlfriend/util/logger.py
girlfriend/util/module.py
girlfriend/util/resource.py
girlfriend/util/script.py
