Metadata-Version: 1.1
Name: girlfriend
Version: 0.0.13
Summary: A pure Python girlfriend she can help you build operation scripts, send data report, monitor the system and do a lot of things you undreamed!The most important, her heart(core lib) is all completely free!
Home-page: http://github.com/chihongze/girlfriend
Author: ChiHongze
Author-email: chihongze@gmail.com
License: MIT
Platform: UNKNOWN
Classifier: Development Status :: 3 - Alpha
Classifier: Environment :: Console
Classifier: Intended Audience :: Developers
Classifier: License :: OSI Approved :: MIT License
Classifier: Operating System :: POSIX
Classifier: Programming Language :: Python
Classifier: Programming Language :: Python :: 2.7
